boltml/__init__.py
boltml_python-0.0.2.dist-info/METADATA
boltml_python-0.0.2.dist-info/WHEEL
boltml_python-0.0.2.dist-info/RECORD
